odoo/addons/endpoint_cache/README.rst
odoo/addons/endpoint_cache/__init__.py
odoo/addons/endpoint_cache/__manifest__.py
odoo/addons/endpoint_cache/i18n/endpoint_cache.pot
odoo/addons/endpoint_cache/i18n/it.po
odoo/addons/endpoint_cache/models/__init__.py
odoo/addons/endpoint_cache/models/endpoint_mixin.py
odoo/addons/endpoint_cache/readme/CONTRIBUTORS.rst
odoo/addons/endpoint_cache/readme/DESCRIPTION.rst
odoo/addons/endpoint_cache/readme/USAGE.rst
odoo/addons/endpoint_cache/static/description/icon.png
odoo/addons/endpoint_cache/static/description/index.html
odoo/addons/endpoint_cache/tests/__init__.py
odoo/addons/endpoint_cache/tests/test_endpoint.py
odoo/addons/endpoint_cache/views/endpoint_view.xml
odoo14_addon_endpoint_cache-14.0.1.2.0.dist-info/METADATA
odoo14_addon_endpoint_cache-14.0.1.2.0.dist-info/WHEEL
odoo14_addon_endpoint_cache-14.0.1.2.0.dist-info/top_level.txt
odoo14_addon_endpoint_cache-14.0.1.2.0.dist-info/RECORD
